<?xml version="1.0" encoding="UTF-8"?>
<data>
    <AU_AzureServiceBusTarget>
        <au_messageid><![CDATA[]]></au_messageid>
        <au_permissionMask><![CDATA[770]]></au_permissionMask>
        <au_entityName><![CDATA[bd_ASB_Target_text_No_Split]]></au_entityName>
        <au_groupOwner><![CDATA[IndigoGroup:192168001075148181566048300002]]></au_groupOwner>
        <au_activeVersion><![CDATA[1]]></au_activeVersion>
        <au_azureServiceBusType><![CDATA[Topic]]></au_azureServiceBusType>
        <au_queue><![CDATA[]]></au_queue>
        <au_usedInTemplateOrTransaction><![CDATA[0]]></au_usedInTemplateOrTransaction>
        <au_correlationid><![CDATA[]]></au_correlationid>
        <au_labelandsubject><![CDATA[]]></au_labelandsubject>
        <au_messageTypes><![CDATA[plaintext]]></au_messageTypes>
        <au_sessionId><![CDATA[bd_ASB_Target_text_No_Split]]></au_sessionId>
        <au_userOwner><![CDATA[IndigoUser:1432581182713565184]]></au_userOwner>
        <au_contenttype><![CDATA[text/plain]]></au_contenttype>
        <au_synchronized><![CDATA[0]]></au_synchronized>
        <au_modifiedDate><![CDATA[2025-12-04T04:22:42]]></au_modifiedDate>
        <au_replyto><![CDATA[]]></au_replyto>
        <au_batchSize><![CDATA[1]]></au_batchSize>
        <au_description><![CDATA[bd_ASB_Target_text_No_Split]]></au_description>
        <au_enableMessageSplitter><![CDATA[0]]></au_enableMessageSplitter>
        <au_projectOwner><![CDATA[Project:11484550701988]]></au_projectOwner>
        <au_topic><![CDATA[bd_topic]]></au_topic>
        <au_messageSplitter><![CDATA[]]></au_messageSplitter>
        <au_azureServiceBusAccount><![CDATA[1445602427456090112]]></au_azureServiceBusAccount>
        <au_revision><![CDATA[null]]></au_revision>
        <au_version><![CDATA[1]]></au_version>
        <au_to><![CDATA[]]></au_to>
        <au_id><![CDATA[1445624800823619584]]></au_id>
        <au_comments><![CDATA[null]]></au_comments>
        <au_customProperty><![CDATA[[]]]></au_customProperty>
        <au_creationDate><![CDATA[2025-12-03T03:56:51]]></au_creationDate>
        <au_previousVersion><![CDATA[]]></au_previousVersion>
        <au_modifiedBy><![CDATA[IndigoUser:1432581182713565184]]></au_modifiedBy>
    </AU_AzureServiceBusTarget>
    <columnInfo dbtype="4">
        <column name="au_id" type="12"/>
        <column name="au_version" type="12"/>
        <column name="au_previousVersion" type="12"/>
        <column name="au_activeVersion" type="3"/>
        <column name="au_entityName" type="12"/>
        <column name="au_userOwner" type="12"/>
        <column name="au_groupOwner" type="12"/>
        <column name="au_permissionMask" type="12"/>
        <column name="au_description" type="12"/>
        <column name="au_comments" type="12"/>
        <column name="au_modifiedBy" type="12"/>
        <column name="au_creationDate" type="93"/>
        <column name="au_modifiedDate" type="93"/>
        <column name="au_revision" type="12"/>
        <column name="au_synchronized" type="3"/>
        <column name="au_projectOwner" type="12"/>
        <column name="au_azureServiceBusAccount" type="12"/>
        <column name="au_azureServiceBusType" type="12"/>
        <column name="au_topic" type="12"/>
        <column name="au_queue" type="12"/>
        <column name="au_enableMessageSplitter" type="3"/>
        <column name="au_messageTypes" type="12"/>
        <column name="au_messageSplitter" type="12"/>
        <column name="au_contenttype" type="12"/>
        <column name="au_correlationid" type="12"/>
        <column name="au_messageid" type="12"/>
        <column name="au_labelandsubject" type="12"/>
        <column name="au_replyto" type="12"/>
        <column name="au_to" type="12"/>
        <column name="au_customProperty" type="-1"/>
        <column name="au_batchSize" type="3"/>
        <column name="au_sessionId" type="12"/>
        <column name="au_usedInTemplateOrTransaction" type="3"/>
    </columnInfo>
</data>
