<?xml version="1.0" encoding="UTF-8"?>
<data>
    <AC_TEMPLATE_METADATA>
        <REFERENCE_FIELD><![CDATA[null]]></REFERENCE_FIELD>
        <TYPE><![CDATA[IndigoTransaction]]></TYPE>
        <ACTIVITY_ID><![CDATA[1445854619676127232]]></ACTIVITY_ID>
        <SERVICE_VARIABLE><![CDATA[null]]></SERVICE_VARIABLE>
        <FILE_NAME><![CDATA[null]]></FILE_NAME>
        <ALIAS_NAME><![CDATA[null]]></ALIAS_NAME>
        <TARGET_FILE_EXTENSION><![CDATA[null]]></TARGET_FILE_EXTENSION>
        <SEQUENCE_ID><![CDATA[-1]]></SEQUENCE_ID>
        <TRANSACTION_TEMPLATE_ID><![CDATA[1446081370939596800]]></TRANSACTION_TEMPLATE_ID>
        <ACCOUNT_ID><![CDATA[null]]></ACCOUNT_ID>
        <SEQUENCE_TYPE><![CDATA[IndigoTransaction]]></SEQUENCE_TYPE>
        <PARAMETER_JSON><![CDATA[[{"id":"1441672744797966336","name":"KG_CSTSource1","type":"LanFileSource","baseType":"Source","trigger":true,"action":false,"include":true,"label":"KG_CSTSource1","serviceDisplayName":"Source","triggerLayout":false,"actionLayout":false,"eventContextEnabled":true,"references":null,"sequenceId":1,"formType":"TRANSACTION","displayName":"KG_CSTSource1","description":"","override":true,"triggerOrAction":false},{"id":"1441673063909003264","name":"KG_CST_SourceLayout1","type":"ExcelSchema","baseType":"SourceSchema","trigger":false,"action":false,"include":true,"label":"KG_CST_SourceLayout1","serviceDisplayName":"Source Layout","triggerLayout":false,"actionLayout":false,"eventContextEnabled":false,"references":[{"id":"1441672744797966336","name":"KG_CSTSource1","type":"LanFileSource","baseType":"Source","trigger":true,"action":false,"include":true,"label":"KG_CSTSource1","serviceDisplayName":"Source","triggerLayout":false,"actionLayout":false,"eventContextEnabled":true,"references":null,"sequenceId":1,"formType":"TEMPLATE"},{"id":"1441673587995676672","name":"KG_CSTMap1","type":"DataMapping","baseType":"DataMapping","trigger":false,"action":false,"include":true,"label":"KG_CSTMap1","serviceDisplayName":"Mapping","triggerLayout":false,"actionLayout":false,"eventContextEnabled":false,"references":null,"sequenceId":6,"formType":"TEMPLATE"}],"sequenceId":2,"formType":"TEMPLATE","displayName":"KG_CST_SourceLayout1","description":"","override":true,"triggerOrAction":false},{"id":"1441672864595374080","name":"KG_CSTTarget1","type":"LanFileTarget","baseType":"Target","trigger":false,"action":true,"include":true,"label":"KG_CSTTarget1","serviceDisplayName":"Target","triggerLayout":false,"actionLayout":false,"eventContextEnabled":false,"references":null,"sequenceId":3,"formType":"TEMPLATE","displayName":"KG_CSTTarget1","description":"","override":true,"triggerOrAction":false},{"id":"1441673319690244096","name":"KG_SimpleTargetlayout1","type":"TextSchema","baseType":"TargetSchema","trigger":false,"action":false,"include":true,"label":"KG_SimpleTargetlayout1","serviceDisplayName":"Target Layout","triggerLayout":false,"actionLayout":false,"eventContextEnabled":false,"references":[{"id":"1441672864595374080","name":"KG_CSTTarget1","type":"LanFileTarget","baseType":"Target","trigger":false,"action":true,"include":true,"label":"KG_CSTTarget1","serviceDisplayName":"Target","triggerLayout":false,"actionLayout":false,"eventContextEnabled":false,"references":null,"sequenceId":3,"formType":"TEMPLATE"},{"id":"1441673587995676672","name":"KG_CSTMap1","type":"DataMapping","baseType":"DataMapping","trigger":false,"action":false,"include":true,"label":"KG_CSTMap1","serviceDisplayName":"Mapping","triggerLayout":false,"actionLayout":false,"eventContextEnabled":false,"references":null,"sequenceId":6,"formType":"TEMPLATE"}],"sequenceId":4,"formType":"TEMPLATE","displayName":"KG_SimpleTargetlayout1","description":"","override":true,"triggerOrAction":false},{"id":"SPAWN-0","name":"Spawn","type":"Spawn","baseType":"Target","trigger":false,"action":false,"include":true,"label":"Spawn","serviceDisplayName":"Target","triggerLayout":false,"actionLayout":false,"eventContextEnabled":false,"references":null,"sequenceId":5,"formType":"TEMPLATE","displayName":"Spawn","description":"","override":true,"triggerOrAction":false},{"id":"1441673587995676672","name":"KG_CSTMap1","type":"DataMapping","baseType":"DataMapping","trigger":false,"action":false,"include":true,"label":"KG_CSTMap1","serviceDisplayName":"Mapping","triggerLayout":false,"actionLayout":false,"eventContextEnabled":false,"references":null,"sequenceId":6,"formType":"TEMPLATE","displayName":"KG_CSTMap1","description":"","override":true,"triggerOrAction":false},{"id":"1443291009983782912","name":"KG_CST_CP_ChildStatus_Dummy","type":"CustomPlugin","baseType":"CustomPlugin","trigger":false,"action":false,"include":true,"label":"KG_CST_CP_ChildStatus_Dummy","serviceDisplayName":"Custom Plugin","triggerLayout":false,"actionLayout":false,"eventContextEnabled":false,"references":null,"sequenceId":7,"formType":"TEMPLATE","displayName":"KG_CST_CP_ChildStatus_Dummy","description":"","override":true,"triggerOrAction":false},{"id":"1443291339584774144","name":"KG_CSTParent_AbortStatus","type":"CustomPlugin","baseType":"CustomPlugin","trigger":false,"action":false,"include":true,"label":"KG_CSTParent_AbortStatus","serviceDisplayName":"Custom Plugin","triggerLayout":false,"actionLayout":false,"eventContextEnabled":false,"references":null,"sequenceId":8,"formType":"TEMPLATE","displayName":"KG_CSTParent_AbortStatus","description":"","override":true,"triggerOrAction":false}]]]></PARAMETER_JSON>
        <TRANSACTION_ENTITY_JSON><![CDATA[null]]></TRANSACTION_ENTITY_JSON>
        <IS_UNIQUE_FILE><![CDATA[false]]></IS_UNIQUE_FILE>
        <ID><![CDATA[1446081451751251968]]></ID>
        <OPERATION><![CDATA[null]]></OPERATION>
        <EXTERNAL_ID><![CDATA[null]]></EXTERNAL_ID>
        <APP_TYPE><![CDATA[null]]></APP_TYPE>
        <DISCRIMINATOR_TYPE><![CDATA[null]]></DISCRIMINATOR_TYPE>
    </AC_TEMPLATE_METADATA>
    <AC_TEMPLATE_METADATA>
        <REFERENCE_FIELD><![CDATA[null]]></REFERENCE_FIELD>
        <TYPE><![CDATA[ExcelSchema]]></TYPE>
        <ACTIVITY_ID><![CDATA[1438608951343493120]]></ACTIVITY_ID>
        <SERVICE_VARIABLE><![CDATA[null]]></SERVICE_VARIABLE>
        <FILE_NAME><![CDATA[null]]></FILE_NAME>
        <ALIAS_NAME><![CDATA[KG_CST_SourceLayout1]]></ALIAS_NAME>
        <TARGET_FILE_EXTENSION><![CDATA[null]]></TARGET_FILE_EXTENSION>
        <SEQUENCE_ID><![CDATA[null]]></SEQUENCE_ID>
        <TRANSACTION_TEMPLATE_ID><![CDATA[1446081370939596800]]></TRANSACTION_TEMPLATE_ID>
        <ACCOUNT_ID><![CDATA[null]]></ACCOUNT_ID>
        <SEQUENCE_TYPE><![CDATA[Schema]]></SEQUENCE_TYPE>
        <PARAMETER_JSON><![CDATA[null]]></PARAMETER_JSON>
        <TRANSACTION_ENTITY_JSON><![CDATA[null]]></TRANSACTION_ENTITY_JSON>
        <IS_UNIQUE_FILE><![CDATA[false]]></IS_UNIQUE_FILE>
        <ID><![CDATA[1446083367906070528]]></ID>
        <OPERATION><![CDATA[null]]></OPERATION>
        <EXTERNAL_ID><![CDATA[null]]></EXTERNAL_ID>
        <APP_TYPE><![CDATA[null]]></APP_TYPE>
        <DISCRIMINATOR_TYPE><![CDATA[null]]></DISCRIMINATOR_TYPE>
    </AC_TEMPLATE_METADATA>
    <AC_TEMPLATE_METADATA>
        <REFERENCE_FIELD><![CDATA[null]]></REFERENCE_FIELD>
        <TYPE><![CDATA[FtpTarget]]></TYPE>
        <ACTIVITY_ID><![CDATA[1446083465058734080]]></ACTIVITY_ID>
        <SERVICE_VARIABLE><![CDATA[null]]></SERVICE_VARIABLE>
        <FILE_NAME><![CDATA[null]]></FILE_NAME>
        <ALIAS_NAME><![CDATA[KG_CSTTarget1]]></ALIAS_NAME>
        <TARGET_FILE_EXTENSION><![CDATA[null]]></TARGET_FILE_EXTENSION>
        <SEQUENCE_ID><![CDATA[null]]></SEQUENCE_ID>
        <TRANSACTION_TEMPLATE_ID><![CDATA[1446081370939596800]]></TRANSACTION_TEMPLATE_ID>
        <ACCOUNT_ID><![CDATA[1439177287661199360]]></ACCOUNT_ID>
        <SEQUENCE_TYPE><![CDATA[Action]]></SEQUENCE_TYPE>
        <PARAMETER_JSON><![CDATA[null]]></PARAMETER_JSON>
        <TRANSACTION_ENTITY_JSON><![CDATA[null]]></TRANSACTION_ENTITY_JSON>
        <IS_UNIQUE_FILE><![CDATA[false]]></IS_UNIQUE_FILE>
        <ID><![CDATA[1446083419105939456]]></ID>
        <OPERATION><![CDATA[null]]></OPERATION>
        <EXTERNAL_ID><![CDATA[null]]></EXTERNAL_ID>
        <APP_TYPE><![CDATA[null]]></APP_TYPE>
        <DISCRIMINATOR_TYPE><![CDATA[null]]></DISCRIMINATOR_TYPE>
    </AC_TEMPLATE_METADATA>
    <AC_TEMPLATE_METADATA>
        <REFERENCE_FIELD><![CDATA[null]]></REFERENCE_FIELD>
        <TYPE><![CDATA[ExcelSchema]]></TYPE>
        <ACTIVITY_ID><![CDATA[1438608951343493120]]></ACTIVITY_ID>
        <SERVICE_VARIABLE><![CDATA[null]]></SERVICE_VARIABLE>
        <FILE_NAME><![CDATA[null]]></FILE_NAME>
        <ALIAS_NAME><![CDATA[KG_SimpleTargetlayout1]]></ALIAS_NAME>
        <TARGET_FILE_EXTENSION><![CDATA[null]]></TARGET_FILE_EXTENSION>
        <SEQUENCE_ID><![CDATA[null]]></SEQUENCE_ID>
        <TRANSACTION_TEMPLATE_ID><![CDATA[1446081370939596800]]></TRANSACTION_TEMPLATE_ID>
        <ACCOUNT_ID><![CDATA[null]]></ACCOUNT_ID>
        <SEQUENCE_TYPE><![CDATA[Schema]]></SEQUENCE_TYPE>
        <PARAMETER_JSON><![CDATA[null]]></PARAMETER_JSON>
        <TRANSACTION_ENTITY_JSON><![CDATA[null]]></TRANSACTION_ENTITY_JSON>
        <IS_UNIQUE_FILE><![CDATA[false]]></IS_UNIQUE_FILE>
        <ID><![CDATA[1446084723882610688]]></ID>
        <OPERATION><![CDATA[null]]></OPERATION>
        <EXTERNAL_ID><![CDATA[null]]></EXTERNAL_ID>
        <APP_TYPE><![CDATA[null]]></APP_TYPE>
        <DISCRIMINATOR_TYPE><![CDATA[null]]></DISCRIMINATOR_TYPE>
    </AC_TEMPLATE_METADATA>
    <AC_TEMPLATE_METADATA>
        <REFERENCE_FIELD><![CDATA[null]]></REFERENCE_FIELD>
        <TYPE><![CDATA[IndigoTransaction]]></TYPE>
        <ACTIVITY_ID><![CDATA[1443289554223636480]]></ACTIVITY_ID>
        <SERVICE_VARIABLE><![CDATA[null]]></SERVICE_VARIABLE>
        <FILE_NAME><![CDATA[null]]></FILE_NAME>
        <ALIAS_NAME><![CDATA[Spawn]]></ALIAS_NAME>
        <TARGET_FILE_EXTENSION><![CDATA[null]]></TARGET_FILE_EXTENSION>
        <SEQUENCE_ID><![CDATA[null]]></SEQUENCE_ID>
        <TRANSACTION_TEMPLATE_ID><![CDATA[1446081370939596800]]></TRANSACTION_TEMPLATE_ID>
        <ACCOUNT_ID><![CDATA[null]]></ACCOUNT_ID>
        <SEQUENCE_TYPE><![CDATA[Target]]></SEQUENCE_TYPE>
        <PARAMETER_JSON><![CDATA[null]]></PARAMETER_JSON>
        <TRANSACTION_ENTITY_JSON><![CDATA[null]]></TRANSACTION_ENTITY_JSON>
        <IS_UNIQUE_FILE><![CDATA[false]]></IS_UNIQUE_FILE>
        <ID><![CDATA[1446084749459857408]]></ID>
        <OPERATION><![CDATA[null]]></OPERATION>
        <EXTERNAL_ID><![CDATA[null]]></EXTERNAL_ID>
        <APP_TYPE><![CDATA[null]]></APP_TYPE>
        <DISCRIMINATOR_TYPE><![CDATA[null]]></DISCRIMINATOR_TYPE>
    </AC_TEMPLATE_METADATA>
    <AC_TEMPLATE_METADATA>
        <REFERENCE_FIELD><![CDATA[null]]></REFERENCE_FIELD>
        <TYPE><![CDATA[CustomPlugin]]></TYPE>
        <ACTIVITY_ID><![CDATA[1446086961522823168]]></ACTIVITY_ID>
        <SERVICE_VARIABLE><![CDATA[null]]></SERVICE_VARIABLE>
        <FILE_NAME><![CDATA[null]]></FILE_NAME>
        <ALIAS_NAME><![CDATA[KG_CSTParent_AbortStatus]]></ALIAS_NAME>
        <TARGET_FILE_EXTENSION><![CDATA[null]]></TARGET_FILE_EXTENSION>
        <SEQUENCE_ID><![CDATA[null]]></SEQUENCE_ID>
        <TRANSACTION_TEMPLATE_ID><![CDATA[1446081370939596800]]></TRANSACTION_TEMPLATE_ID>
        <ACCOUNT_ID><![CDATA[null]]></ACCOUNT_ID>
        <SEQUENCE_TYPE><![CDATA[CustomPlugin]]></SEQUENCE_TYPE>
        <PARAMETER_JSON><![CDATA[null]]></PARAMETER_JSON>
        <TRANSACTION_ENTITY_JSON><![CDATA[null]]></TRANSACTION_ENTITY_JSON>
        <IS_UNIQUE_FILE><![CDATA[false]]></IS_UNIQUE_FILE>
        <ID><![CDATA[1446086971929272320]]></ID>
        <OPERATION><![CDATA[null]]></OPERATION>
        <EXTERNAL_ID><![CDATA[null]]></EXTERNAL_ID>
        <APP_TYPE><![CDATA[null]]></APP_TYPE>
        <DISCRIMINATOR_TYPE><![CDATA[null]]></DISCRIMINATOR_TYPE>
    </AC_TEMPLATE_METADATA>
    <AC_TEMPLATE_METADATA>
        <REFERENCE_FIELD><![CDATA[null]]></REFERENCE_FIELD>
        <TYPE><![CDATA[CustomPlugin]]></TYPE>
        <ACTIVITY_ID><![CDATA[1446087291434573824]]></ACTIVITY_ID>
        <SERVICE_VARIABLE><![CDATA[null]]></SERVICE_VARIABLE>
        <FILE_NAME><![CDATA[null]]></FILE_NAME>
        <ALIAS_NAME><![CDATA[KG_CST_CP_ChildStatus_Dummy]]></ALIAS_NAME>
        <TARGET_FILE_EXTENSION><![CDATA[null]]></TARGET_FILE_EXTENSION>
        <SEQUENCE_ID><![CDATA[null]]></SEQUENCE_ID>
        <TRANSACTION_TEMPLATE_ID><![CDATA[1446081370939596800]]></TRANSACTION_TEMPLATE_ID>
        <ACCOUNT_ID><![CDATA[null]]></ACCOUNT_ID>
        <SEQUENCE_TYPE><![CDATA[CustomPlugin]]></SEQUENCE_TYPE>
        <PARAMETER_JSON><![CDATA[null]]></PARAMETER_JSON>
        <TRANSACTION_ENTITY_JSON><![CDATA[null]]></TRANSACTION_ENTITY_JSON>
        <IS_UNIQUE_FILE><![CDATA[false]]></IS_UNIQUE_FILE>
        <ID><![CDATA[1446087306785345536]]></ID>
        <OPERATION><![CDATA[null]]></OPERATION>
        <EXTERNAL_ID><![CDATA[null]]></EXTERNAL_ID>
        <APP_TYPE><![CDATA[null]]></APP_TYPE>
        <DISCRIMINATOR_TYPE><![CDATA[null]]></DISCRIMINATOR_TYPE>
    </AC_TEMPLATE_METADATA>
    <AC_TEMPLATE_METADATA>
        <REFERENCE_FIELD><![CDATA[null]]></REFERENCE_FIELD>
        <TYPE><![CDATA[DataMapping]]></TYPE>
        <ACTIVITY_ID><![CDATA[1446088252521586688]]></ACTIVITY_ID>
        <SERVICE_VARIABLE><![CDATA[null]]></SERVICE_VARIABLE>
        <FILE_NAME><![CDATA[null]]></FILE_NAME>
        <ALIAS_NAME><![CDATA[KG_CSTMap1]]></ALIAS_NAME>
        <TARGET_FILE_EXTENSION><![CDATA[null]]></TARGET_FILE_EXTENSION>
        <SEQUENCE_ID><![CDATA[null]]></SEQUENCE_ID>
        <TRANSACTION_TEMPLATE_ID><![CDATA[1446081370939596800]]></TRANSACTION_TEMPLATE_ID>
        <ACCOUNT_ID><![CDATA[null]]></ACCOUNT_ID>
        <SEQUENCE_TYPE><![CDATA[Mapping]]></SEQUENCE_TYPE>
        <PARAMETER_JSON><![CDATA[null]]></PARAMETER_JSON>
        <TRANSACTION_ENTITY_JSON><![CDATA[null]]></TRANSACTION_ENTITY_JSON>
        <IS_UNIQUE_FILE><![CDATA[false]]></IS_UNIQUE_FILE>
        <ID><![CDATA[1446088275627626496]]></ID>
        <OPERATION><![CDATA[null]]></OPERATION>
        <EXTERNAL_ID><![CDATA[null]]></EXTERNAL_ID>
        <APP_TYPE><![CDATA[null]]></APP_TYPE>
        <DISCRIMINATOR_TYPE><![CDATA[null]]></DISCRIMINATOR_TYPE>
    </AC_TEMPLATE_METADATA>
    <columnInfo dbtype="0">
        <column name="ID" type="-5"/>
        <column name="ACCOUNT_ID" type="12"/>
        <column name="ACTIVITY_ID" type="12"/>
        <column name="DISCRIMINATOR_TYPE" type="12"/>
        <column name="FILE_NAME" type="-1"/>
        <column name="IS_UNIQUE_FILE" type="-7"/>
        <column name="SEQUENCE_ID" type="4"/>
        <column name="SEQUENCE_TYPE" type="12"/>
        <column name="SERVICE_VARIABLE" type="-1"/>
        <column name="TARGET_FILE_EXTENSION" type="12"/>
        <column name="APP_TYPE" type="12"/>
        <column name="TYPE" type="12"/>
        <column name="OPERATION" type="12"/>
        <column name="REFERENCE_FIELD" type="-1"/>
        <column name="TRANSACTION_ENTITY_JSON" type="12"/>
        <column name="EXTERNAL_ID" type="12"/>
        <column name="TRANSACTION_TEMPLATE_ID" type="-5"/>
        <column name="PARAMETER_JSON" type="-1"/>
        <column name="ALIAS_NAME" type="12"/>
    </columnInfo>
</data>
